./.gitignore
./PKG-INFO
./README.md
./__init__.py
./__main__.py
./pyproject.toml
./requirements.txt
./server.py
./unified_router.py
./tests/__init__.py
./tests/test_green_phase.py
./tests/test_security.py
./tests/test_unified_router.py
slash_commands/.gitignore
slash_commands/PKG-INFO
slash_commands/README.md
slash_commands/__init__.py
slash_commands/__main__.py
slash_commands/pyproject.toml
slash_commands/requirements.txt
slash_commands/server.py
slash_commands/unified_router.py
slash_commands/artifacts/performance_test_results.json
slash_commands/tests/__init__.py
slash_commands/tests/test_green_phase.py
slash_commands/tests/test_security.py
slash_commands/tests/test_unified_router.py
claude_slash_commands_mcp-1.0.0.dist-info/METADATA
claude_slash_commands_mcp-1.0.0.dist-info/WHEEL
claude_slash_commands_mcp-1.0.0.dist-info/entry_points.txt
claude_slash_commands_mcp-1.0.0.dist-info/RECORD
